{"name":"User should be able to create a new account for the application","id":"new-user-sign-up;user-should-be-able-to-create-a-new-account-for-the-application","testSteps":[{"number":1,"description":"Given Customer data is available for new user","duration":587,"startTime":"2019-10-12T01:22:52.576+05:30[Asia/Kolkata]","result":"SUCCESS","reportData":[{"title":"Generated customer Data","contents":"CustomerDataDTO(firstName\u003dMatt, LastName\u003dLubowitz, emailId\u003dsaul.roberts@gmail.com, password\u003d76161852, birthday\u003d10, birthMonth\u003d2, birthYear\u003d1988, companyName\u003dAdrian Zieme, address1\u003d0334 Hattie Street, address2\u003dSuite 196, city\u003dLiaton, state\u003d4, zipCode\u003d95176, otherInfo\u003dStrickland, homeNo\u003d509-006-1814, mobileNo\u003d(013) 179-2392, alias\u003dHF Challenge)","isEvidence":false,"id":"report-data-ad666e72-7764-4aac-b441-51ccfc3e0463"}],"precondition":false,"level":0},{"number":2,"description":"Given Matt, a new customer navigates to application sign in page","duration":10679,"startTime":"2019-10-12T01:22:53.164+05:30[Asia/Kolkata]","result":"SUCCESS","precondition":false,"level":0,"children":[{"number":3,"description":"Navigate to sign in page","duration":10675,"startTime":"2019-10-12T01:22:53.167+05:30[Asia/Kolkata]","result":"SUCCESS","precondition":false,"level":1}]},{"number":4,"description":"When Matt registers as a new user of the application","duration":6934,"startTime":"2019-10-12T01:23:03.843+05:30[Asia/Kolkata]","result":"SUCCESS","precondition":false,"level":0,"children":[{"number":5,"description":"Proceed to create account after providing email id","duration":598,"startTime":"2019-10-12T01:23:03.845+05:30[Asia/Kolkata]","result":"SUCCESS","precondition":false,"level":1},{"number":6,"description":"Create account","duration":4566,"startTime":"2019-10-12T01:23:06.210+05:30[Asia/Kolkata]","result":"SUCCESS","precondition":false,"level":1}]},{"number":7,"description":"Then Matt should get logged into the application","duration":150,"startTime":"2019-10-12T01:23:10.778+05:30[Asia/Kolkata]","result":"SUCCESS","precondition":false,"level":0},{"number":8,"description":"And Matt should be able to view his account page","duration":132,"startTime":"2019-10-12T01:23:10.929+05:30[Asia/Kolkata]","result":"SUCCESS","precondition":false,"level":0},{"number":9,"description":"And view the sign out option","duration":38,"startTime":"2019-10-12T01:23:11.062+05:30[Asia/Kolkata]","result":"SUCCESS","precondition":false,"level":0}],"userStory":{"id":"new-user-sign-up","storyName":"New user sign up","path":"userlogin/user_signup.feature","narrative":"  As a new customer of the shopping website\n  I should be able to sign up with my email id\n  So that I can login to the application","type":"feature"},"featureTag":{"name":"Userlogin/New user sign up","type":"feature","displayName":"Userlogin/New user sign up"},"title":"User should be able to create a new account for the application","backgroundTitle":"Generate new customer data","backgroundDescription":"","tags":[{"name":"run","type":"tag","displayName":"run"}],"startTime":"2019-10-12T01:22:52.571+05:30[Asia/Kolkata]","duration":18530,"projectKey":"","sessionId":"8f565b64c3cbab42a385cad523bda427","driver":"chrome","isManualTestingUpToDate":false,"manual":false,"testSource":"Cucumber","result":"SUCCESS"}